iranges/utils.py
iranges/lib_iranges.cpython-313-x86_64-linux-musl.so
iranges/sew_handler.py
iranges/irangeslist.py
iranges/IRanges.py
iranges/__init__.py
iranges-0.7.2.dist-info/WHEEL
iranges-0.7.2.dist-info/top_level.txt
iranges-0.7.2.dist-info/METADATA
iranges-0.7.2.dist-info/RECORD
iranges-0.7.2.dist-info/licenses/LICENSE.txt
iranges.libs/libstdc++-0d31ccbe.so.6.0.32
iranges.libs/libgcc_s-a0b57c20.so.1
