Metadata-Version: 2.4
Name: IRanges
Version: 0.7.2
Summary: Python implementation of the [**IRanges**](https://bioconductor.org/packages/IRanges) Bioconductor package.
Home-page: https://github.com/biocpy/iranges
Author: LTLA
Author-email: infinite.monkeys.with.keyboards@gmail.com
License: MIT
Project-URL: Documentation, https://github.com/biocpy/iranges
Platform: any
Classifier: Development Status :: 4 - Beta
Classifier: Programming Language :: Python
Requires-Python: >=3.9
License-File: LICENSE.txt
Requires-Dist: importlib-metadata; python_version < "3.8"
Requires-Dist: biocutils>=0.3.3
Requires-Dist: biocframe>=0.7.2
Requires-Dist: compressed_lists>=0.4.3
Requires-Dist: numpy
Provides-Extra: optional
Requires-Dist: polars; extra == "optional"
Requires-Dist: pandas; extra == "optional"
Provides-Extra: testing
Requires-Dist: setuptools; extra == "testing"
Requires-Dist: pytest; extra == "testing"
Requires-Dist: pytest-cov; extra == "testing"
Requires-Dist: pandas; extra == "testing"
Requires-Dist: polars; extra == "testing"
Dynamic: license-file
